flake8_ascii_validator.py
flake8_ascii_validator-1.0.2.dist-info/licenses/LICENSE
flake8_ascii_validator-1.0.2.dist-info/METADATA
flake8_ascii_validator-1.0.2.dist-info/WHEEL
flake8_ascii_validator-1.0.2.dist-info/entry_points.txt
flake8_ascii_validator-1.0.2.dist-info/top_level.txt
flake8_ascii_validator-1.0.2.dist-info/RECORD
