Metadata-Version: 2.4
Name: flake8-ascii-validator
Version: 1.0.2
Summary: A Flake8 plugin to validate ASCII characters in Python source code
Author-email: Shiv Kumar <shivkumar0757@gmail.com>
Maintainer-email: Shiv Kumar <shivkumar0757@gmail.com>
License-Expression: MIT
Project-URL: Homepage, https://github.com/shivkumar0757/flake8-ascii-validator
Project-URL: Repository, https://github.com/shivkumar0757/flake8-ascii-validator
Project-URL: Bug Tracker, https://github.com/shivkumar0757/flake8-ascii-validator/issues
Project-URL: Documentation, https://github.com/shivkumar0757/flake8-ascii-validator#readme
Keywords: flake8,plugin,ascii,validation,code-quality,linting
Classifier: Development Status :: 4 - Beta
Classifier: Environment :: Console
Classifier: Framework :: Flake8
Classifier: Intended Audience :: Developers
Classifier: Operating System :: OS Independent
Classifier: Programming Language :: Python
Classifier: Programming Language :: Python :: 3
Classifier: Programming Language :: Python :: 3.7
Classifier: Programming Language :: Python :: 3.8
Classifier: Programming Language :: Python :: 3.9
Classifier: Programming Language :: Python :: 3.10
Classifier: Programming Language :: Python :: 3.11
Classifier: Programming Language :: Python :: 3.12
Classifier: Topic :: Software Development :: Libraries :: Python Modules
Classifier: Topic :: Software Development :: Quality Assurance
Requires-Python: >=3.7
License-File: LICENSE
Requires-Dist: flake8>=3.0.0
Provides-Extra: test
Requires-Dist: pytest>=6.0; extra == "test"
Requires-Dist: pytest-cov; extra == "test"
Requires-Dist: flake8; extra == "test"
Provides-Extra: dev
Requires-Dist: pytest>=6.0; extra == "dev"
Requires-Dist: pytest-cov; extra == "dev"
Requires-Dist: flake8; extra == "dev"
Requires-Dist: black; extra == "dev"
Requires-Dist: isort; extra == "dev"
Requires-Dist: build; extra == "dev"
Requires-Dist: twine; extra == "dev"
Dynamic: license-file
